directory_observer/__init__.py
directory_observer/directory_observer.py
directory_observer-1.0.1.dist-info/LICENSE
directory_observer-1.0.1.dist-info/METADATA
directory_observer-1.0.1.dist-info/WHEEL
directory_observer-1.0.1.dist-info/top_level.txt
directory_observer-1.0.1.dist-info/RECORD
