Metadata-Version: 2.1
Name: directory-observer
Version: 1.0.1
Home-page: https://github.com/ChsHub/directory_observer
Author: ChsHub
License: MIT License
Classifier: Programming Language :: Python :: 3
Classifier: Topic :: Software Development
Classifier: Topic :: Utilities
License-File: LICENSE
